sdam
