Metadata-Version: 1.1
Name: sdam
Version: 0.4.4
Summary: (s)tart programs (d)aemonized (a)nd (m)onitored.
Home-page: http://launchpad.net/sdam
Author: Oleksandr Kozachuk
Author-email: ddeus.lp@mailnull.com
License: WTFPL
Download-URL: https://pypi.python.org/pypi/SDAM
Keywords: daemon monitoring service
Platform: UNKNOWN
